[{"line":1,"elements":[{"line":3,"name":"","description":"","type":"background","keyword":"Background","steps":[{"result":{"duration":42909000000,"status":"passed"},"line":4,"name":"Launch web application","match":{"location":"stepDefinitions.MyStepdefs.launch_web_application()"},"keyword":"Given "}]},{"start_timestamp":"2022-09-02T22:14:51.111Z","line":8,"name":"Successful Login Authentication","description":"","id":"test-scenarios-for-saucelabs;successful-login-authentication","after":[{"result":{"duration":8360000000,"status":"passed"},"match":{"location":"stepDefinitions.MyStepdefs.closeBrowser()"}}],"type":"scenario","keyword":"Scenario","steps":[{"result":{"duration":990000000,"status":"passed"},"line":9,"name":"Enter \"standard_user\" for login","match":{"arguments":[{"val":"standard_user","offset":7}],"location":"stepDefinitions.MyStepdefs.enterForLogin(java.lang.String)"},"keyword":"Given "},{"result":{"duration":2067000000,"status":"passed"},"line":10,"name":"Enter \"secret_sauce\" and click login button","match":{"arguments":[{"val":"secret_sauce","offset":7}],"location":"stepDefinitions.MyStepdefs.enterAndClickLoginButton(java.lang.String)"},"keyword":"Then "},{"result":{"duration":448000000,"status":"passed"},"line":11,"name":"Validate the successful login","match":{"location":"stepDefinitions.MyStepdefs.validateTheSuccessfulLogin()"},"keyword":"And "}],"tags":[{"name":"@Success"},{"name":"@SauceLabTest"}]},{"line":3,"name":"","description":"","type":"background","keyword":"Background","steps":[{"result":{"duration":17366000000,"status":"passed"},"line":4,"name":"Launch web application","match":{"location":"stepDefinitions.MyStepdefs.launch_web_application()"},"keyword":"Given "}]},{"start_timestamp":"2022-09-02T22:15:46.550Z","line":21,"name":"Un-happy path to validate the login errors","description":"","id":"test-scenarios-for-saucelabs;un-happy-path-to-validate-the-login-errors;;2","after":[{"result":{"duration":2450000000,"status":"passed"},"match":{"location":"stepDefinitions.MyStepdefs.closeBrowser()"}}],"type":"scenario","keyword":"Scenario Outline","steps":[{"result":{"duration":294000000,"status":"passed"},"line":16,"name":"Enter \"\" for login","match":{"arguments":[{"val":"","offset":7}],"location":"stepDefinitions.MyStepdefs.enterForLogin(java.lang.String)"},"keyword":"Given "},{"result":{"duration":868000000,"status":"passed"},"line":17,"name":"Enter \"\" and click login button","match":{"arguments":[{"val":"","offset":7}],"location":"stepDefinitions.MyStepdefs.enterAndClickLoginButton(java.lang.String)"},"keyword":"Then "},{"result":{"duration":244000000,"status":"passed"},"line":18,"name":"Validate the \"Epic sadface: Username is required\"","match":{"arguments":[{"val":"Epic sadface: Username is required","offset":14}],"location":"stepDefinitions.MyStepdefs.validateThe(java.lang.String)"},"keyword":"And "}],"tags":[{"name":"@NegativeScenarios"},{"name":"@SauceLabTest"}]},{"line":3,"name":"","description":"","type":"background","keyword":"Background","steps":[{"result":{"duration":19622000000,"status":"passed"},"line":4,"name":"Launch web application","match":{"location":"stepDefinitions.MyStepdefs.launch_web_application()"},"keyword":"Given "}]},{"start_timestamp":"2022-09-02T22:16:07.885Z","line":22,"name":"Un-happy path to validate the login errors","description":"","id":"test-scenarios-for-saucelabs;un-happy-path-to-validate-the-login-errors;;3","after":[{"result":{"duration":2737000000,"status":"passed"},"match":{"location":"stepDefinitions.MyStepdefs.closeBrowser()"}}],"type":"scenario","keyword":"Scenario Outline","steps":[{"result":{"duration":820000000,"status":"passed"},"line":16,"name":"Enter \"\" for login","match":{"arguments":[{"val":"","offset":7}],"location":"stepDefinitions.MyStepdefs.enterForLogin(java.lang.String)"},"keyword":"Given "},{"result":{"duration":1121000000,"status":"passed"},"line":17,"name":"Enter \"test\" and click login button","match":{"arguments":[{"val":"test","offset":7}],"location":"stepDefinitions.MyStepdefs.enterAndClickLoginButton(java.lang.String)"},"keyword":"Then "},{"result":{"duration":250000000,"status":"passed"},"line":18,"name":"Validate the \"Epic sadface: Username is required\"","match":{"arguments":[{"val":"Epic sadface: Username is required","offset":14}],"location":"stepDefinitions.MyStepdefs.validateThe(java.lang.String)"},"keyword":"And "}],"tags":[{"name":"@NegativeScenarios"},{"name":"@SauceLabTest"}]},{"line":3,"name":"","description":"","type":"background","keyword":"Background","steps":[{"result":{"error_message":"org.openqa.selenium.WebDriverException: Timed out waiting for driver server to start.\nBuild info: version: '3.12.0', revision: '7c6e0b3', time: '2018-05-08T14:04:26.12Z'\nSystem info: host: 'LTIE000091', ip: '10.122.117.157', os.name: 'Windows 10', os.arch: 'amd64', os.version: '10.0', java.version: '1.8.0_291'\nDriver info: driver.version: ChromeDriver\r\n\tat org.openqa.selenium.remote.service.DriverService.waitUntilAvailable(DriverService.java:192)\r\n\tat org.openqa.selenium.remote.service.DriverService.start(DriverService.java:178)\r\n\tat org.openqa.selenium.remote.service.DriverCommandExecutor.execute(DriverCommandExecutor.java:79)\r\n\tat org.openqa.selenium.remote.RemoteWebDriver.execute(RemoteWebDriver.java:543)\r\n\tat org.openqa.selenium.remote.RemoteWebDriver.startSession(RemoteWebDriver.java:207)\r\n\tat org.openqa.selenium.remote.RemoteWebDriver.<init>(RemoteWebDriver.java:130)\r\n\tat org.openqa.selenium.chrome.ChromeDriver.<init>(ChromeDriver.java:181)\r\n\tat org.openqa.selenium.chrome.ChromeDriver.<init>(ChromeDriver.java:168)\r\n\tat org.openqa.selenium.chrome.ChromeDriver.<init>(ChromeDriver.java:123)\r\n\tat Utilities.BrowserFactory.initializeDriver(BrowserFactory.java:11)\r\n\tat stepDefinitions.MyStepdefs.launch_web_application(MyStepdefs.java:36)\r\n\tat ✽.Launch web application(file:///C:/Dell/src/test/resources/features/SauceLab.feature:4)\r\nCaused by: org.openqa.selenium.net.UrlChecker$TimeoutException: Timed out waiting for [http://localhost:37034/status] to be available after 20012 ms\r\n\tat org.openqa.selenium.net.UrlChecker.waitUntilAvailable(UrlChecker.java:100)\r\n\tat org.openqa.selenium.remote.service.DriverService.waitUntilAvailable(DriverService.java:187)\r\n\tat org.openqa.selenium.remote.service.DriverService.start(DriverService.java:178)\r\n\tat org.openqa.selenium.remote.service.DriverCommandExecutor.execute(DriverCommandExecutor.java:79)\r\n\tat org.openqa.selenium.remote.RemoteWebDriver.execute(RemoteWebDriver.java:543)\r\n\tat org.openqa.selenium.remote.RemoteWebDriver.startSession(RemoteWebDriver.java:207)\r\n\tat org.openqa.selenium.remote.RemoteWebDriver.<init>(RemoteWebDriver.java:130)\r\n\tat org.openqa.selenium.chrome.ChromeDriver.<init>(ChromeDriver.java:181)\r\n\tat org.openqa.selenium.chrome.ChromeDriver.<init>(ChromeDriver.java:168)\r\n\tat org.openqa.selenium.chrome.ChromeDriver.<init>(ChromeDriver.java:123)\r\n\tat Utilities.BrowserFactory.initializeDriver(BrowserFactory.java:11)\r\n\tat stepDefinitions.MyStepdefs.launch_web_application(MyStepdefs.java:36)\r\n\tat sun.reflect.NativeMethodAccessorImpl.invoke0(Native Method)\r\n\tat sun.reflect.NativeMethodAccessorImpl.invoke(NativeMethodAccessorImpl.java:62)\r\n\tat sun.reflect.DelegatingMethodAccessorImpl.invoke(DelegatingMethodAccessorImpl.java:43)\r\n\tat java.lang.reflect.Method.invoke(Method.java:498)\r\n\tat io.cucumber.java.Invoker.doInvoke(Invoker.java:66)\r\n\tat io.cucumber.java.Invoker.invoke(Invoker.java:24)\r\n\tat io.cucumber.java.AbstractGlueDefinition.invokeMethod(AbstractGlueDefinition.java:47)\r\n\tat io.cucumber.java.JavaStepDefinition.execute(JavaStepDefinition.java:29)\r\n\tat io.cucumber.core.runner.CoreStepDefinition.execute(CoreStepDefinition.java:66)\r\n\tat io.cucumber.core.runner.PickleStepDefinitionMatch.runStep(PickleStepDefinitionMatch.java:63)\r\n\tat io.cucumber.core.runner.ExecutionMode$1.execute(ExecutionMode.java:10)\r\n\tat io.cucumber.core.runner.TestStep.executeStep(TestStep.java:85)\r\n\tat io.cucumber.core.runner.TestStep.run(TestStep.java:57)\r\n\tat io.cucumber.core.runner.PickleStepTestStep.run(PickleStepTestStep.java:51)\r\n\tat io.cucumber.core.runner.TestCase.run(TestCase.java:84)\r\n\tat io.cucumber.core.runner.Runner.runPickle(Runner.java:75)\r\n\tat io.cucumber.junit.PickleRunners$NoStepDescriptions.lambda$run$0(PickleRunners.java:151)\r\n\tat io.cucumber.core.runtime.CucumberExecutionContext.lambda$runTestCase$5(CucumberExecutionContext.java:129)\r\n\tat io.cucumber.core.runtime.RethrowingThrowableCollector.executeAndThrow(RethrowingThrowableCollector.java:23)\r\n\tat io.cucumber.core.runtime.CucumberExecutionContext.runTestCase(CucumberExecutionContext.java:129)\r\n\tat io.cucumber.junit.PickleRunners$NoStepDescriptions.run(PickleRunners.java:148)\r\n\tat io.cucumber.junit.FeatureRunner.runChild(FeatureRunner.java:144)\r\n\tat io.cucumber.junit.FeatureRunner.runChild(FeatureRunner.java:28)\r\n\tat org.junit.runners.ParentRunner$4.run(ParentRunner.java:331)\r\n\tat org.junit.runners.ParentRunner$1.schedule(ParentRunner.java:79)\r\n\tat org.junit.runners.ParentRunner.runChildren(ParentRunner.java:329)\r\n\tat org.junit.runners.ParentRunner.access$100(ParentRunner.java:66)\r\n\tat org.junit.runners.ParentRunner$2.evaluate(ParentRunner.java:293)\r\n\tat org.junit.runners.ParentRunner$3.evaluate(ParentRunner.java:306)\r\n\tat org.junit.runners.ParentRunner.run(ParentRunner.java:413)\r\n\tat io.cucumber.junit.FeatureRunner.run(FeatureRunner.java:137)\r\n\tat io.cucumber.junit.Cucumber.runChild(Cucumber.java:196)\r\n\tat io.cucumber.junit.Cucumber.runChild(Cucumber.java:89)\r\n\tat org.junit.runners.ParentRunner$4.run(ParentRunner.java:331)\r\n\tat org.junit.runners.ParentRunner$1.schedule(ParentRunner.java:79)\r\n\tat org.junit.runners.ParentRunner.runChildren(ParentRunner.java:329)\r\n\tat org.junit.runners.ParentRunner.access$100(ParentRunner.java:66)\r\n\tat org.junit.runners.ParentRunner$2.evaluate(ParentRunner.java:293)\r\n\tat io.cucumber.junit.Cucumber$RunBeforeAllHooks.evaluate(Cucumber.java:266)\r\n\tat io.cucumber.junit.Cucumber$RunAfterAllHooks.evaluate(Cucumber.java:281)\r\n\tat io.cucumber.junit.Cucumber$StartTestRun.evaluate(Cucumber.java:233)\r\n\tat io.cucumber.junit.Cucumber$FinishTestRun.evaluate(Cucumber.java:248)\r\n\tat org.junit.runners.ParentRunner$3.evaluate(ParentRunner.java:306)\r\n\tat org.junit.runners.ParentRunner.run(ParentRunner.java:413)\r\n\tat org.junit.runner.JUnitCore.run(JUnitCore.java:137)\r\n\tat com.intellij.junit4.JUnit4IdeaTestRunner.startRunnerWithArgs(JUnit4IdeaTestRunner.java:69)\r\n\tat com.intellij.rt.junit.IdeaTestRunner$Repeater.startRunnerWithArgs(IdeaTestRunner.java:33)\r\n\tat com.intellij.rt.junit.JUnitStarter.prepareStreamsAndStart(JUnitStarter.java:221)\r\n\tat com.intellij.rt.junit.JUnitStarter.main(JUnitStarter.java:54)\r\nCaused by: java.util.concurrent.TimeoutException\r\n\tat java.util.concurrent.FutureTask.get(FutureTask.java:205)\r\n\tat com.google.common.util.concurrent.SimpleTimeLimiter.callWithTimeout(SimpleTimeLimiter.java:148)\r\n\tat org.openqa.selenium.net.UrlChecker.waitUntilAvailable(UrlChecker.java:75)\r\n\t... 60 more\r\n","duration":20170000000,"status":"failed"},"line":4,"name":"Launch web application","match":{"location":"stepDefinitions.MyStepdefs.launch_web_application()"},"keyword":"Given "}]},{"start_timestamp":"2022-09-02T22:16:32.516Z","line":23,"name":"Un-happy path to validate the login errors","description":"","id":"test-scenarios-for-saucelabs;un-happy-path-to-validate-the-login-errors;;4","after":[{"result":{"error_message":"java.lang.NullPointerException\r\n\tat stepDefinitions.MyStepdefs.closeBrowser(MyStepdefs.java:30)\r\n","status":"failed"},"match":{"location":"stepDefinitions.MyStepdefs.closeBrowser()"}}],"type":"scenario","keyword":"Scenario Outline","steps":[{"result":{"status":"skipped"},"line":16,"name":"Enter \"test\" for login","match":{"arguments":[{"val":"test","offset":7}],"location":"stepDefinitions.MyStepdefs.enterForLogin(java.lang.String)"},"keyword":"Given "},{"result":{"status":"skipped"},"line":17,"name":"Enter \"\" and click login button","match":{"arguments":[{"val":"","offset":7}],"location":"stepDefinitions.MyStepdefs.enterAndClickLoginButton(java.lang.String)"},"keyword":"Then "},{"result":{"status":"skipped"},"line":18,"name":"Validate the \"Epic sadface: Password is required\"","match":{"arguments":[{"val":"Epic sadface: Password is required","offset":14}],"location":"stepDefinitions.MyStepdefs.validateThe(java.lang.String)"},"keyword":"And "}],"tags":[{"name":"@NegativeScenarios"},{"name":"@SauceLabTest"}]},{"line":3,"name":"","description":"","type":"background","keyword":"Background","steps":[{"result":{"duration":23834000000,"status":"passed"},"line":4,"name":"Launch web application","match":{"location":"stepDefinitions.MyStepdefs.launch_web_application()"},"keyword":"Given "}]},{"start_timestamp":"2022-09-02T22:16:52.889Z","line":24,"name":"Un-happy path to validate the login errors","description":"","id":"test-scenarios-for-saucelabs;un-happy-path-to-validate-the-login-errors;;5","after":[{"result":{"duration":3065000000,"status":"passed"},"match":{"location":"stepDefinitions.MyStepdefs.closeBrowser()"}}],"type":"scenario","keyword":"Scenario Outline","steps":[{"result":{"duration":1537000000,"status":"passed"},"line":16,"name":"Enter \"Test\" for login","match":{"arguments":[{"val":"Test","offset":7}],"location":"stepDefinitions.MyStepdefs.enterForLogin(java.lang.String)"},"keyword":"Given "},{"result":{"duration":964000000,"status":"passed"},"line":17,"name":"Enter \"Random\" and click login button","match":{"arguments":[{"val":"Random","offset":7}],"location":"stepDefinitions.MyStepdefs.enterAndClickLoginButton(java.lang.String)"},"keyword":"Then "},{"result":{"duration":219000000,"status":"passed"},"line":18,"name":"Validate the \"Epic sadface: Username and password do not match any user in this service\"","match":{"arguments":[{"val":"Epic sadface: Username and password do not match any user in this service","offset":14}],"location":"stepDefinitions.MyStepdefs.validateThe(java.lang.String)"},"keyword":"And "}],"tags":[{"name":"@NegativeScenarios"},{"name":"@SauceLabTest"}]},{"line":3,"name":"","description":"","type":"background","keyword":"Background","steps":[{"result":{"duration":16955000000,"status":"passed"},"line":4,"name":"Launch web application","match":{"location":"stepDefinitions.MyStepdefs.launch_web_application()"},"keyword":"Given "}]},{"start_timestamp":"2022-09-02T22:17:22.614Z","line":25,"name":"Un-happy path to validate the login errors","description":"","id":"test-scenarios-for-saucelabs;un-happy-path-to-validate-the-login-errors;;6","after":[{"result":{"duration":16993000000,"status":"passed"},"match":{"location":"stepDefinitions.MyStepdefs.closeBrowser()"}}],"type":"scenario","keyword":"Scenario Outline","steps":[{"result":{"duration":1557000000,"status":"passed"},"line":16,"name":"Enter \"standard_user\" for login","match":{"arguments":[{"val":"standard_user","offset":7}],"location":"stepDefinitions.MyStepdefs.enterForLogin(java.lang.String)"},"keyword":"Given "},{"result":{"duration":891000000,"status":"passed"},"line":17,"name":"Enter \"sejior\" and click login button","match":{"arguments":[{"val":"sejior","offset":7}],"location":"stepDefinitions.MyStepdefs.enterAndClickLoginButton(java.lang.String)"},"keyword":"Then "},{"result":{"duration":346000000,"status":"passed"},"line":18,"name":"Validate the \"Epic sadface: Username and password do not match any user in this service\"","match":{"arguments":[{"val":"Epic sadface: Username and password do not match any user in this service","offset":14}],"location":"stepDefinitions.MyStepdefs.validateThe(java.lang.String)"},"keyword":"And "}],"tags":[{"name":"@NegativeScenarios"},{"name":"@SauceLabTest"}]},{"line":3,"name":"","description":"","type":"background","keyword":"Background","steps":[{"result":{"duration":29413000000,"status":"passed"},"line":4,"name":"Launch web application","match":{"location":"stepDefinitions.MyStepdefs.launch_web_application()"},"keyword":"Given "}]},{"start_timestamp":"2022-09-02T22:18:03.380Z","line":29,"name":"Successful purchase of product","description":"","id":"test-scenarios-for-saucelabs;successful-purchase-of-product","after":[{"result":{"duration":7526000000,"status":"passed"},"match":{"location":"stepDefinitions.MyStepdefs.closeBrowser()"}}],"type":"scenario","keyword":"Scenario","steps":[{"result":{"duration":1634000000,"status":"passed"},"line":30,"name":"Enter \"standard_user\" for login","match":{"arguments":[{"val":"standard_user","offset":7}],"location":"stepDefinitions.MyStepdefs.enterForLogin(java.lang.String)"},"keyword":"Given "},{"result":{"duration":1650000000,"status":"passed"},"line":31,"name":"Enter \"secret_sauce\" and click login button","match":{"arguments":[{"val":"secret_sauce","offset":7}],"location":"stepDefinitions.MyStepdefs.enterAndClickLoginButton(java.lang.String)"},"keyword":"Then "},{"result":{"duration":2279000000,"status":"passed"},"line":32,"name":"Validate the successful login","match":{"location":"stepDefinitions.MyStepdefs.validateTheSuccessfulLogin()"},"keyword":"And "},{"result":{"duration":1882000000,"status":"passed"},"line":33,"name":"Add two products to cart","match":{"location":"stepDefinitions.MyStepdefs.addTwoProductsToCart()"},"keyword":"Then "},{"result":{"duration":2487000000,"status":"passed"},"line":34,"name":"Enter the checkout details \"Ben\" \"Geller\" and \"D04VW50\" and click checkout","match":{"arguments":[{"val":"Ben","offset":28},{"val":"Geller","offset":34},{"val":"D04VW50","offset":47}],"location":"stepDefinitions.MyStepdefs.enterTheCheckoutDetailsAndAndClickCheckout(java.lang.String,java.lang.String,java.lang.String)"},"keyword":"And "},{"result":{"duration":2902000000,"status":"passed"},"line":35,"name":"Verify the details and click Review","match":{"location":"stepDefinitions.MyStepdefs.verifyTheDetailsAndClickReview()"},"keyword":"Then "}],"tags":[{"name":"@LoginBuy2Product"},{"name":"@SauceLabTest"}]}],"name":"Test scenarios for Saucelabs","description":"","id":"test-scenarios-for-saucelabs","keyword":"Feature","uri":"file:src/test/resources/features/SauceLab.feature","tags":[]}]